notes/__init__.py
notes/cli.py
notes/config.py
notes/constants.py
notes/helpers.py
notes/commands/__init__.py
notes/commands/add.py
notes/commands/init.py
notes/commands/list.py
notes/commands/notebooks.py
notes/commands/open.py
notes/commands/remove.py
notes/commands/sync.py
notes_md-0.1.2.dist-info/licenses/LICENSE
notes_md-0.1.2.dist-info/METADATA
notes_md-0.1.2.dist-info/WHEEL
notes_md-0.1.2.dist-info/entry_points.txt
notes_md-0.1.2.dist-info/top_level.txt
notes_md-0.1.2.dist-info/RECORD
