Metadata-Version: 2.4
Name: notes-md
Version: 0.1.2
Summary: Markdown based notes CLI that uses current directory as the notebook name.
Author: David Knight
License: MIT
Project-URL: Homepage, https://github.com/viacoffee/notes-md
Project-URL: Repository, https://github.com/viacoffee/notes-md
Requires-Python: >=3.8
License-File: LICENSE
Requires-Dist: click>=8.1
Requires-Dist: PyYAML>=6.0
Provides-Extra: dev
Requires-Dist: pytest>=8.0; extra == "dev"
Dynamic: license-file
